setup.cfg
setup.py
beam_interactive/__init__.py
beam_interactive/connection.py
beam_interactive/exceptions.py
beam_interactive/helpers.py
beam_interactive.egg-info/PKG-INFO
beam_interactive.egg-info/SOURCES.txt
beam_interactive.egg-info/dependency_links.txt
beam_interactive.egg-info/requires.txt
beam_interactive.egg-info/top_level.txt
beam_interactive/proto/__init__.py
beam_interactive/proto/identifier.py
beam_interactive/proto/rw.py
beam_interactive/proto/tetris_pb2.py
beam_interactive/proto/varint.py