Metadata-Version: 1.1
Name: beam-interactive
Version: 0.2.1
Summary: reference Robot implementation for Beam Interactive
Home-page: https://github.com/WatchBeam/beam-interactive-python
Author: Connor Peet
Author-email: connor@peet.io
License: MIT
Platform: UNKNOWN
Classifier: Development Status :: 2 - Pre-Alpha
Classifier: Programming Language :: Python :: 3.3
Classifier: Programming Language :: Python :: 3.4
Classifier: Programming Language :: Python :: 3.5
Classifier: License :: OSI Approved :: MIT License
Classifier: Topic :: Games/Entertainment
Classifier: Topic :: Software Development
Classifier: Topic :: Software Development :: Libraries
